fpga/i2c/i2c.v
// Copyright 2024
// Bryce's Senior Project
// Description: This is the RTL for the I2C which communicates between the PWM controller and the encoder.
module i2c(
    input               reset_n,        // Active low reset
    input               clock,          // The main clock
    input               angle_done,     // Whether or not we are at the target angle
    output      [11:0]  raw_angle,      // The raw angle from the AS5600            
    output              scl,            // The I2C clock
    inout               sda             // The I2C bi-directional data
);

localparam      ENCODER_ADDRESS     = 7'h36;
localparam      CLOCK_DIV_RATIO     = 6'h32;

localparam      IDLE        = 4'h0;
localparam      START       = 4'h1;
localparam      DEV_WR      = 4'h2;
localparam      ACK0        = 4'h3;
localparam      READ_ADDR   = 4'h4;
localparam      ACK1        = 4'h5;
localparam      REP_START   = 4'h6;
localparam      DEV_RD      = 4'h7;
localparam      ACK2        = 4'h8;
localparam      DATA0       = 4'h9;
localparam      ACK3        = 4'hA;
localparam      DATA1       = 4'hB;
localparam      NACK        = 4'hC;
localparam      STOP        = 4'hD;
localparam      PAUSE       = 4'hE;

localparam      WRITE_DEVICE    = 8'h6C;
localparam      READ_DEVICE     = 8'h6D;
localparam      READ_RAW_ANGLE  = 8'h0C;

reg     [2:0]   bit_counter;
reg     [3:0]   ns, ps;
reg     [1:0]   substate;
wire            PHASE1, PHASE2, PHASE3, PHASE4;
reg             scl_int, sda_int, tri_mode;
reg             wr_bit, rd_bit;
reg     [7:0]   read_data0, read_data1;

always @(posedge clock or negedge reset_n) begin
    if(~reset_n) begin
        substate[1:0]   <= 2'h0;
        wr_bit          <= 1'h0;
        read_data0[7:0] <= 8'b0;
        read_data1[7:0] <= 8'b0;
    end
    else begin
        substate[1:0]   <= substate[1:0] + 2'h1;
        if(ps == DEV_WR)
            wr_bit        <= WRITE_DEVICE[8'd7 - bit_counter];
        else if(ps == READ_ADDR)
            wr_bit        <= READ_RAW_ANGLE[8'd7 - bit_counter];
        else if(ps == DEV_RD)
            wr_bit        <= READ_DEVICE[8'd7 - bit_counter];
        else
            wr_bit    <= 1'bx;

        if((ps == DATA0) & PHASE3)
            read_data1[8'd7 - bit_counter] = rd_bit;
        
        else if((ps == DATA1) & PHASE3)
            read_data0[8'd7 - bit_counter] = rd_bit;
    end
end

assign PHASE1 = (substate[1:0] == 2'b00);
assign PHASE2 = (substate[1:0] == 2'b01);
assign PHASE3 = (substate[1:0] == 2'b10);
assign PHASE4 = (substate[1:0] == 2'b11);

always @(posedge PHASE1 or negedge reset_n) begin
    if(~reset_n) begin
        ps              <= IDLE;
        bit_counter     <= 3'b0;        
    end
    else begin
        ps <= ns;        
        if((ps == DEV_WR) | (ps == READ_ADDR) | (ps == DEV_RD) | (ps == DATA0) | (ps == DATA1))
            bit_counter <= bit_counter + 3'h1;
        else
            bit_counter <= 3'h0;        
    end
end

always @(*) begin
    case(ps)
        IDLE: begin
            if(~angle_done)
                ns = START;
            else
                ns = IDLE;
        end

        START: begin
            ns = DEV_WR;
        end

        DEV_WR: begin
            if(bit_counter == 4'h7)
                ns = ACK0;
            else
                ns = DEV_WR;
        end

        ACK0: begin
            ns = READ_ADDR;
        end

        READ_ADDR: begin
            if(bit_counter == 4'h7)
                ns = ACK1;
            else
                ns = READ_ADDR;
        end

        ACK1: begin
            ns = REP_START;
        end


        REP_START: begin
            ns = DEV_RD;
        end

        DEV_RD: begin
            if(bit_counter == 4'h7)
                ns = ACK2;
            else
                ns = DEV_RD; 
        end

        ACK2: begin
            ns = DATA0;
        end

        DATA0: begin
            if(bit_counter == 4'h7)
                ns = ACK3;
            else
                ns = DATA0;
        end

        ACK3: begin
            ns = DATA1;
        end

        DATA1: begin
            if(bit_counter == 4'h7)
                ns = NACK;
            else 
                ns = DATA1;
        end

        NACK: begin
            ns = STOP;
        end

        STOP: begin
            ns = PAUSE;
        end

        PAUSE: begin
            if(angle_done)
                ns = IDLE;
            else
                ns = START;
        end

        default: begin
            ns = IDLE;
        end
    endcase
end

// I2C Clock and Data driver
always @(*) begin
    scl_int     = 1'b1;
    sda_int     = 1'b1;
    tri_mode    = 1'b0;

    case(ps)
        IDLE: begin
            scl_int = 1'b1;
            sda_int = 1'b1;
        end

        START: begin
            //  A high-to-low transition on the SDA line while the SCL is high defines a START condition
            tri_mode    = 1'b0;
            if(PHASE1) begin
                scl_int = 1'b1;
                sda_int = 1'b1;
            end 
            else if(PHASE2) begin
                scl_int = 1'b1;
                sda_int = 1'b0;
            end
             else if(PHASE3) begin
                scl_int = 1'b1;
                sda_int = 1'b0;
            end
             else if(PHASE4) begin
                scl_int = 1'b0;
                sda_int = 1'b0;
            end
        end

        DEV_WR: begin
            tri_mode    = 1'b0;
            if(PHASE1) begin
                scl_int = 1'b0;
                sda_int = wr_bit;
            end 
            else if(PHASE2) begin
                scl_int = 1'b0;
                sda_int = wr_bit;
            end
             else if(PHASE3) begin
                scl_int = 1'b1;
                sda_int = wr_bit;
            end
             else if(PHASE4) begin
                scl_int = 1'b1;
                sda_int = wr_bit;
            end
        end

        ACK0: begin
            tri_mode = 1'b1;
            if(PHASE1) begin
                scl_int = 1'b0;
                sda_int = 1'bZ;
            end 
            else if(PHASE2) begin
                scl_int = 1'b0;
                sda_int = 1'bZ;
            end
             else if(PHASE3) begin
                scl_int = 1'b1;
                sda_int = 1'bZ;
            end
             else if(PHASE4) begin
                scl_int = 1'b1;
                sda_int = 1'bZ;
            end
        end

        READ_ADDR: begin
            // The SDA is x during the 1st phase because the address calculation requires that we flop it (verilog issue)
            // But its value is stable before the clock rise.
            tri_mode    = 1'b0;
            if(PHASE1) begin
                scl_int = 1'b0;
                sda_int = wr_bit;
            end 
            else if(PHASE2) begin
                scl_int = 1'b0;
                sda_int = wr_bit;
            end
             else if(PHASE3) begin
                scl_int = 1'b1;
                sda_int = wr_bit;
            end
             else if(PHASE4) begin
                scl_int = 1'b1;
                sda_int = wr_bit;
            end
        end

        ACK1: begin
            tri_mode = 1'b1;
            if(PHASE1) begin
                scl_int = 1'b0;
                sda_int = 1'bZ;
            end 
            else if(PHASE2) begin
                scl_int = 1'b0;
                sda_int = 1'bZ;
            end
             else if(PHASE3) begin
                scl_int = 1'b1;
                sda_int = 1'bZ;
            end
             else if(PHASE4) begin
                scl_int = 1'b1;
                sda_int = 1'bZ;
            end
        end

        REP_START: begin
            tri_mode    = 1'b0;
            if(PHASE1) begin
                scl_int = 1'b0;
                sda_int = 1'b0;
            end 
            else if(PHASE2) begin
                scl_int = 1'b0;
                sda_int = 1'b1;
            end
             else if(PHASE3) begin
                scl_int = 1'b1;
                sda_int = 1'b1;
            end
             else if(PHASE4) begin
                scl_int = 1'b1;
                sda_int = 1'b0;
            end
        end

        DEV_RD: begin
            tri_mode    = 1'b0;
            if(PHASE1) begin
                scl_int = 1'b0;
                sda_int = wr_bit;
            end 
            else if(PHASE2) begin
                scl_int = 1'b0;
                sda_int = wr_bit;
            end
             else if(PHASE3) begin
                scl_int = 1'b1;
                sda_int = wr_bit;
            end
             else if(PHASE4) begin
                scl_int = 1'b1;
                sda_int = wr_bit;
            end
        end

        ACK2: begin
            tri_mode = 1'b1;
            if(PHASE1) begin
                scl_int = 1'b0;
                sda_int = 1'bZ;
            end 
            else if(PHASE2) begin
                scl_int = 1'b0;
                sda_int = 1'bZ;
            end
             else if(PHASE3) begin
                scl_int = 1'b1;
                sda_int = 1'bZ;
            end
             else if(PHASE4) begin
                scl_int = 1'b1;
                sda_int = 1'bZ;
            end
        end

        DATA0: begin
            tri_mode = 1'b1;
            if(PHASE1) begin
                scl_int = 1'b0;
                sda_int = 1'bZ;
            end 
            else if(PHASE2) begin
                scl_int = 1'b0;
                sda_int = 1'bZ;
            end
             else if(PHASE3) begin
                scl_int = 1'b1;
                sda_int = 1'bZ;
            end
             else if(PHASE4) begin
                scl_int = 1'b1;
                sda_int = 1'bZ;
                rd_bit  = sda;
            end
        end

        ACK3: begin
            // When reading data the controller has to pull down the SDA to ACK
            tri_mode    = 1'b0;
            if(PHASE1) begin
                scl_int = 1'b0;
                sda_int = 1'b0;
            end 
            else if(PHASE2) begin
                scl_int = 1'b0;
                sda_int = 1'b0;
            end
             else if(PHASE3) begin
                scl_int = 1'b1;
                sda_int = 1'b0;
            end
             else if(PHASE4) begin
                scl_int = 1'b1;
                sda_int = 1'b0;
            end
        end

        DATA1: begin
            tri_mode = 1'b1;
            if(PHASE1) begin
                scl_int = 1'b0;
                sda_int = 1'bZ;
            end 
            else if(PHASE2) begin
                scl_int = 1'b0;
                sda_int = 1'bZ;
            end
             else if(PHASE3) begin
                scl_int = 1'b1;
                sda_int = 1'bZ;
            end
             else if(PHASE4) begin
                scl_int = 1'b1;
                sda_int = 1'bZ;
                rd_bit  = sda;
            end
        end

        NACK: begin
            // In the NACK condition, the controller will drive the SDA to 1
            tri_mode    = 1'b0;
            if(PHASE1) begin
                scl_int = 1'b0;
                sda_int = 1'b1;
            end 
            else if(PHASE2) begin
                scl_int = 1'b0;
                sda_int = 1'b1;
            end
             else if(PHASE3) begin
                scl_int = 1'b1;
                sda_int = 1'b1;
            end
             else if(PHASE4) begin
                scl_int = 1'b1;
                sda_int = 1'b1;
            end   
        end

        STOP: begin
            // The STOP condition occurs after a NACK, we keep the SDA at 1 for the first phase, then pull it low for the 2nd
            // and 3rd phases, then it is pulled high for the 4th phase.
            //A low-to-high transition on the SDA line while the SCL is high defines a STOP condition.
            tri_mode    = 1'b0;
            if(PHASE1) begin
                scl_int = 1'b0;
                sda_int = 1'b1;
            end 
            else if(PHASE2) begin
                scl_int = 1'b0;
                sda_int = 1'b0;
            end
             else if(PHASE3) begin
                scl_int = 1'b1;
                sda_int = 1'b0;
            end
             else if(PHASE4) begin
                scl_int = 1'b1;
                sda_int = 1'b1;
            end 
        end

        PAUSE: begin
            tri_mode= 1'b0;
            scl_int = 1'b1;
            sda_int = 1'b1;
        end

        default: begin
            tri_mode= 1'b0;
            scl_int = 1'b1;
            sda_int = 1'b1;
        end
    endcase    
end

assign scl = scl_int;
assign sda = tri_mode ? 1'bZ : sda_int;
assign raw_angle = {read_data1[11:8], read_data0[7:0]};
endmodule

fpga/i2c/i2c_tb.v
// Copyright 2024
// Bryce's Senior Project
// Description: This is the TestBench for SPI

module test();
  reg clock = 0;
  reg reset_n = 0;
  reg angle_done = 1;
  wire   [11:0] raw_angle;
  wire scl, sda;
  reg sda_temp;

 always
    #1  clock = ~clock;

initial begin
    $display("Starting i2c test");
    sda_temp = 1'bZ;
    
    $display("Deasserting reset");
    #10 reset_n = 1;

    $display("Setting angle_done to 0");
    #10 angle_done = 0;

    #150;
    /* #8 sda_temp = 1'b1;
    #8 sda_temp = 1'b1;
    #8 sda_temp = 1'b0;
    #8 sda_temp = 1'b0;
    #8 sda_temp = 1'b1;
    #8 sda_temp = 1'b0;
    #8 sda_temp = 1'b1;
    #8 sda_temp = 1'b0;
    #8 sda_temp = 1'bZ; */

    #500;

    #10 $finish;
end

assign sda = sda_temp;

i2c dut(
    .clock          (clock),
    .reset_n        (reset_n),
    .angle_done     (angle_done),
    .raw_angle      (raw_angle[11:0]),
    .scl            (scl),
    .sda            (sda)
);

initial begin
    $dumpfile("i2c.vcd");
    $dumpvars(0,test);
  end

endmodule

fpga/i2c/i2c.vcd
$date
	Sun Oct 27 20:34:05 2024
$end
$version
	Icarus Verilog
$end
$timescale
	1s
$end
$scope module test $end
$var wire 1 ! sda $end
$var wire 1 " scl $end
$var wire 12 # raw_angle [11:0] $end
$var reg 1 $ angle_done $end
$var reg 1 % clock $end
$var reg 1 & reset_n $end
$var reg 1 ' sda_temp $end
$scope module dut $end
$var wire 1 $ angle_done $end
$var wire 1 % clock $end
$var wire 1 & reset_n $end
$var wire 1 " scl $end
$var wire 1 ! sda $end
$var wire 12 ( raw_angle [11:0] $end
$var wire 1 ) PHASE4 $end
$var wire 1 * PHASE3 $end
$var wire 1 + PHASE2 $end
$var wire 1 , PHASE1 $end
$var parameter 4 - ACK0 $end
$var parameter 4 . ACK1 $end
$var parameter 4 / ACK2 $end
$var parameter 4 0 ACK3 $end
$var parameter 6 1 CLOCK_DIV_RATIO $end
$var parameter 4 2 DATA0 $end
$var parameter 4 3 DATA1 $end
$var parameter 4 4 DEV_RD $end
$var parameter 4 5 DEV_WR $end
$var parameter 7 6 ENCODER_ADDRESS $end
$var parameter 4 7 IDLE $end
$var parameter 4 8 NACK $end
$var parameter 4 9 PAUSE $end
$var parameter 4 : READ_ADDR $end
$var parameter 8 ; READ_DEVICE $end
$var parameter 8 < READ_RAW_ANGLE $end
$var parameter 4 = REP_START $end
$var parameter 4 > START $end
$var parameter 4 ? STOP $end
$var parameter 8 @ WRITE_DEVICE $end
$var reg 3 A bit_counter [2:0] $end
$var reg 4 B ns [3:0] $end
$var reg 4 C ps [3:0] $end
$var reg 1 D rd_bit $end
$var reg 8 E read_data0 [7:0] $end
$var reg 8 F read_data1 [7:0] $end
$var reg 1 G scl_int $end
$var reg 1 H sda_int $end
$var reg 2 I substate [1:0] $end
$var reg 1 J tri_mode $end
$var reg 1 K wr_bit $end
$upscope $end
$upscope $end
$enddefinitions $end
$comment Show the parameter values. $end
$dumpall
b1101100 @
b1101 ?
b1 >
b110 =
b1100 <
b1101101 ;
b100 :
b1110 9
b1100 8
b0 7
b110110 6
b10 5
b111 4
b1011 3
b1001 2
b110010 1
b1010 0
b1000 /
b101 .
b11 -
$end
#0
$dumpvars
0K
0J
b0 I
1H
1G
b0 F
b0 E
xD
b0 C
b0 B
b0 A
1,
0+
0*
0)
bx00000000 (
z'
0&
0%
1$
bx00000000 #
1"
1!
$end
#1
1%
#2
0%
#3
1%
#4
0%
#5
1%
#6
0%
#7
1%
#8
0%
#9
1%
#10
0%
1&
#11
xK
0,
1+
b1 I
1%
#12
0%
#13
0+
1*
b10 I
1%
#14
0%
#15
0*
1)
b11 I
1%
#16
0%
#17
1,
0)
b0 I
1%
#18
0%
#19
0,
1+
b1 I
1%
#20
b1 B
0%
0$
#21
0+
1*
b10 I
1%
#22
0%
#23
0*
1)
b11 I
1%
#24
0%
#25
b10 B
b1 C
1,
0)
b0 I
1%
#26
0%
#27
0!
0H
0,
1+
b1 I
1%
#28
0%
#29
0H
0+
1*
b10 I
1%
#30
0%
#31
0"
0G
0H
0*
1)
b11 I
1%
#32
0%
#33
b10 C
x!
xH
0"
0G
1,
0)
b0 I
1%
#34
0%
#35
0!
0H
0"
0G
0K
0,
1+
b1 I
1%
#36
0%
#37
0H
1"
1G
0+
1*
b10 I
1%
#38
0%
#39
0H
0*
1)
b11 I
1%
#40
0%
#41
b1 A
0"
0G
0H
1,
0)
b0 I
1%
#42
0%
#43
1!
1H
0"
0G
1K
0,
1+
b1 I
1%
#44
0%
#45
1"
1G
0+
1*
b10 I
1%
#46
0%
#47
0*
1)
b11 I
1%
#48
0%
#49
b10 A
0"
0G
1,
0)
b0 I
1%
#50
0%
#51
0"
0G
0,
1+
b1 I
1%
#52
0%
#53
1"
1G
0+
1*
b10 I
1%
#54
0%
#55
0*
1)
b11 I
1%
#56
0%
#57
b11 A
0"
0G
1,
0)
b0 I
1%
#58
0%
#59
0!
0H
0"
0G
0K
0,
1+
b1 I
1%
#60
0%
#61
0H
1"
1G
0+
1*
b10 I
1%
#62
0%
#63
0H
0*
1)
b11 I
1%
#64
0%
#65
b100 A
0"
0G
0H
1,
0)
b0 I
1%
#66
0%
#67
1!
1H
0"
0G
1K
0,
1+
b1 I
1%
#68
0%
#69
1"
1G
0+
1*
b10 I
1%
#70
0%
#71
0*
1)
b11 I
1%
#72
0%
#73
b101 A
0"
0G
1,
0)
b0 I
1%
#74
0%
#75
0"
0G
0,
1+
b1 I
1%
#76
0%
#77
1"
1G
0+
1*
b10 I
1%
#78
0%
#79
0*
1)
b11 I
1%
#80
0%
#81
b110 A
0"
0G
1,
0)
b0 I
1%
#82
0%
#83
0!
0H
0"
0G
0K
0,
1+
b1 I
1%
#84
0%
#85
0H
1"
1G
0+
1*
b10 I
1%
#86
0%
#87
0H
0*
1)
b11 I
1%
#88
0%
#89
b11 B
b111 A
0"
0G
0H
1,
0)
b0 I
1%
#90
0%
#91
0H
0"
0G
0,
1+
b1 I
1%
#92
0%
#93
0H
1"
1G
0+
1*
b10 I
1%
#94
0%
#95
0H
0*
1)
b11 I
1%
#96
0%
#97
z!
1J
b100 B
b0 A
b11 C
0"
0G
zH
1,
0)
b0 I
1%
#98
0%
#99
1J
zH
0"
0G
xK
0,
1+
b1 I
1%
#100
0%
#101
1J
zH
1"
1G
0+
1*
b10 I
1%
#102
0%
#103
1J
zH
0*
1)
b11 I
1%
#104
0%
#105
x!
b100 C
0"
0G
0J
xH
1,
0)
b0 I
1%
#106
0%
#107
0!
0H
0"
0G
0K
0,
1+
b1 I
1%
#108
0%
#109
0H
1"
1G
0+
1*
b10 I
1%
#110
0%
#111
0H
0*
1)
b11 I
1%
#112
0%
#113
b1 A
0"
0G
0H
1,
0)
b0 I
1%
#114
0%
#115
0H
0"
0G
0,
1+
b1 I
1%
#116
0%
#117
0H
1"
1G
0+
1*
b10 I
1%
#118
0%
#119
0H
0*
1)
b11 I
1%
#120
0%
#121
b10 A
0"
0G
0H
1,
0)
b0 I
1%
#122
0%
#123
0H
0"
0G
0,
1+
b1 I
1%
#124
0%
#125
0H
1"
1G
0+
1*
b10 I
1%
#126
0%
#127
0H
0*
1)
b11 I
1%
#128
0%
#129
b11 A
0"
0G
0H
1,
0)
b0 I
1%
#130
0%
#131
0H
0"
0G
0,
1+
b1 I
1%
#132
0%
#133
0H
1"
1G
0+
1*
b10 I
1%
#134
0%
#135
0H
0*
1)
b11 I
1%
#136
0%
#137
b100 A
0"
0G
0H
1,
0)
b0 I
1%
#138
0%
#139
1!
1H
0"
0G
1K
0,
1+
b1 I
1%
#140
0%
#141
1"
1G
0+
1*
b10 I
1%
#142
0%
#143
0*
1)
b11 I
1%
#144
0%
#145
b101 A
0"
0G
1,
0)
b0 I
1%
#146
0%
#147
0"
0G
0,
1+
b1 I
1%
#148
0%
#149
1"
1G
0+
1*
b10 I
1%
#150
0%
#151
0*
1)
b11 I
1%
#152
0%
#153
b110 A
0"
0G
1,
0)
b0 I
1%
#154
0%
#155
0!
0H
0"
0G
0K
0,
1+
b1 I
1%
#156
0%
#157
0H
1"
1G
0+
1*
b10 I
1%
#158
0%
#159
0H
0*
1)
b11 I
1%
#160
0%
#161
b101 B
b111 A
0"
0G
0H
1,
0)
b0 I
1%
#162
0%
#163
0H
0"
0G
0,
1+
b1 I
1%
#164
0%
#165
0H
1"
1G
0+
1*
b10 I
1%
#166
0%
#167
0H
0*
1)
b11 I
1%
#168
0%
#169
z!
1J
b110 B
b0 A
b101 C
0"
0G
zH
1,
0)
b0 I
1%
#170
0%
#171
1J
zH
0"
0G
xK
0,
1+
b1 I
1%
#172
0%
#173
1J
zH
1"
1G
0+
1*
b10 I
1%
#174
0%
#175
1J
zH
0*
1)
b11 I
1%
#176
0%
#177
0!
b111 B
b110 C
0"
0G
0J
0H
1,
0)
b0 I
1%
#178
0%
#179
1!
1H
0"
0G
0,
1+
b1 I
1%
#180
0%
#181
1"
1G
0+
1*
b10 I
1%
#182
0%
#183
0!
0H
0*
1)
b11 I
1%
#184
0%
#185
x!
b111 C
0"
0G
xH
1,
0)
b0 I
1%
#186
0%
#187
0!
0H
0"
0G
0K
0,
1+
b1 I
1%
#188
0%
#189
0H
1"
1G
0+
1*
b10 I
1%
#190
0%
#191
0H
0*
1)
b11 I
1%
#192
0%
#193
b1 A
0"
0G
0H
1,
0)
b0 I
1%
#194
0%
#195
1!
1H
0"
0G
1K
0,
1+
b1 I
1%
#196
0%
#197
1"
1G
0+
1*
b10 I
1%
#198
0%
#199
0*
1)
b11 I
1%
#200
0%
#201
b10 A
0"
0G
1,
0)
b0 I
1%
#202
0%
#203
0"
0G
0,
1+
b1 I
1%
#204
0%
#205
1"
1G
0+
1*
b10 I
1%
#206
0%
#207
0*
1)
b11 I
1%
#208
0%
#209
b11 A
0"
0G
1,
0)
b0 I
1%
#210
0%
#211
0!
0H
0"
0G
0K
0,
1+
b1 I
1%
#212
0%
#213
0H
1"
1G
0+
1*
b10 I
1%
#214
0%
#215
0H
0*
1)
b11 I
1%
#216
0%
#217
b100 A
0"
0G
0H
1,
0)
b0 I
1%
#218
0%
#219
1!
1H
0"
0G
1K
0,
1+
b1 I
1%
#220
0%
#221
1"
1G
0+
1*
b10 I
1%
#222
0%
#223
0*
1)
b11 I
1%
#224
0%
#225
b101 A
0"
0G
1,
0)
b0 I
1%
#226
0%
#227
0"
0G
0,
1+
b1 I
1%
#228
0%
#229
1"
1G
0+
1*
b10 I
1%
#230
0%
#231
0*
1)
b11 I
1%
#232
0%
#233
b110 A
0"
0G
1,
0)
b0 I
1%
#234
0%
#235
0!
0H
0"
0G
0K
0,
1+
b1 I
1%
#236
0%
#237
0H
1"
1G
0+
1*
b10 I
1%
#238
0%
#239
0H
0*
1)
b11 I
1%
#240
0%
#241
b1000 B
b111 A
0"
0G
0H
1,
0)
b0 I
1%
#242
0%
#243
1!
1H
0"
0G
1K
0,
1+
b1 I
1%
#244
0%
#245
1"
1G
0+
1*
b10 I
1%
#246
0%
#247
0*
1)
b11 I
1%
#248
0%
#249
z!
zH
1J
b1001 B
b0 A
b1000 C
0"
0G
1,
0)
b0 I
1%
#250
0%
#251
1J
zH
0"
0G
xK
0,
1+
b1 I
1%
#252
0%
#253
1J
zH
1"
1G
0+
1*
b10 I
1%
#254
0%
#255
1J
zH
0*
1)
b11 I
1%
#256
0%
#257
b1001 C
0"
0G
1J
zH
1,
0)
b0 I
1%
#258
0%
#259
1J
zH
0"
0G
0,
1+
b1 I
1%
#260
0%
#261
1J
zH
1"
1G
0+
1*
b10 I
1%
#262
0%
#263
zD
1J
zH
0*
1)
b11 I
bx0000000 F
1%
#264
0%
#265
b1 A
0"
0G
1J
zH
1,
0)
b0 I
1%
#266
0%
#267
1J
zH
0"
0G
0,
1+
b1 I
1%
#268
0%
#269
1J
zH
1"
1G
0+
1*
b10 I
1%
#270
0%
#271
1J
zH
0*
1)
b11 I
bxz000000 F
1%
#272
0%
#273
b10 A
0"
0G
1J
zH
1,
0)
b0 I
1%
#274
0%
#275
1J
zH
0"
0G
0,
1+
b1 I
1%
#276
0%
#277
1J
zH
1"
1G
0+
1*
b10 I
1%
#278
0%
#279
1J
zH
0*
1)
b11 I
bxzz00000 F
1%
#280
0%
#281
b11 A
0"
0G
1J
zH
1,
0)
b0 I
1%
#282
0%
#283
1J
zH
0"
0G
0,
1+
b1 I
1%
#284
0%
#285
1J
zH
1"
1G
0+
1*
b10 I
1%
#286
0%
#287
1J
zH
0*
1)
b11 I
bxzzz0000 F
1%
#288
0%
#289
b100 A
0"
0G
1J
zH
1,
0)
b0 I
1%
#290
0%
#291
1J
zH
0"
0G
0,
1+
b1 I
1%
#292
0%
#293
1J
zH
1"
1G
0+
1*
b10 I
1%
#294
0%
#295
1J
zH
0*
1)
b11 I
bxzzzz000 F
1%
#296
0%
#297
b101 A
0"
0G
1J
zH
1,
0)
b0 I
1%
#298
0%
#299
1J
zH
0"
0G
0,
1+
b1 I
1%
#300
0%
#301
1J
zH
1"
1G
0+
1*
b10 I
1%
#302
0%
#303
1J
zH
0*
1)
b11 I
bxzzzzz00 F
1%
#304
0%
#305
b110 A
0"
0G
1J
zH
1,
0)
b0 I
1%
#306
0%
#307
1J
zH
0"
0G
0,
1+
b1 I
1%
#308
0%
#309
1J
zH
1"
1G
0+
1*
b10 I
1%
#310
0%
#311
1J
zH
0*
1)
b11 I
bxzzzzzz0 F
1%
#312
0%
#313
b1010 B
b111 A
0"
0G
1J
zH
1,
0)
b0 I
1%
#314
0%
#315
1J
zH
0"
0G
0,
1+
b1 I
1%
#316
0%
#317
1J
zH
1"
1G
0+
1*
b10 I
1%
#318
0%
#319
1J
zH
0*
1)
b11 I
bxzzzzzzz F
1%
#320
0%
#321
0!
b1011 B
b0 A
b1010 C
0"
0G
0J
0H
1,
0)
b0 I
1%
#322
0%
#323
0H
0"
0G
0,
1+
b1 I
1%
#324
0%
#325
0H
1"
1G
0+
1*
b10 I
1%
#326
0%
#327
0H
0*
1)
b11 I
1%
#328
0%
#329
z!
1J
b1011 C
0"
0G
zH
1,
0)
b0 I
1%
#330
0%
#331
1J
zH
0"
0G
0,
1+
b1 I
1%
#332
0%
#333
1J
zH
1"
1G
0+
1*
b10 I
1%
#334
0%
#335
1J
zH
0*
1)
b11 I
bxz0000000 #
bxz0000000 (
bz0000000 E
1%
#336
0%
#337
b1 A
0"
0G
1J
zH
1,
0)
b0 I
1%
#338
0%
#339
1J
zH
0"
0G
0,
1+
b1 I
1%
#340
0%
#341
1J
zH
1"
1G
0+
1*
b10 I
1%
#342
0%
#343
1J
zH
0*
1)
b11 I
bxzz000000 #
bxzz000000 (
bz000000 E
1%
#344
0%
#345
b10 A
0"
0G
1J
zH
1,
0)
b0 I
1%
#346
0%
#347
1J
zH
0"
0G
0,
1+
b1 I
1%
#348
0%
#349
1J
zH
1"
1G
0+
1*
b10 I
1%
#350
0%
#351
1J
zH
0*
1)
b11 I
bxzzz00000 #
bxzzz00000 (
bz00000 E
1%
#352
0%
#353
b11 A
0"
0G
1J
zH
1,
0)
b0 I
1%
#354
0%
#355
1J
zH
0"
0G
0,
1+
b1 I
1%
#356
0%
#357
1J
zH
1"
1G
0+
1*
b10 I
1%
#358
0%
#359
1J
zH
0*
1)
b11 I
bxzzzz0000 #
bxzzzz0000 (
bz0000 E
1%
#360
0%
#361
b100 A
0"
0G
1J
zH
1,
0)
b0 I
1%
#362
0%
#363
1J
zH
0"
0G
0,
1+
b1 I
1%
#364
0%
#365
1J
zH
1"
1G
0+
1*
b10 I
1%
#366
0%
#367
1J
zH
0*
1)
b11 I
bxzzzzz000 #
bxzzzzz000 (
bz000 E
1%
#368
0%
#369
b101 A
0"
0G
1J
zH
1,
0)
b0 I
1%
#370
0%
#371
1J
zH
0"
0G
0,
1+
b1 I
1%
#372
0%
#373
1J
zH
1"
1G
0+
1*
b10 I
1%
#374
0%
#375
1J
zH
0*
1)
b11 I
bxzzzzzz00 #
bxzzzzzz00 (
bz00 E
1%
#376
0%
#377
b110 A
0"
0G
1J
zH
1,
0)
b0 I
1%
#378
0%
#379
1J
zH
0"
0G
0,
1+
b1 I
1%
#380
0%
#381
1J
zH
1"
1G
0+
1*
b10 I
1%
#382
0%
#383
1J
zH
0*
1)
b11 I
bxzzzzzzz0 #
bxzzzzzzz0 (
bz0 E
1%
#384
0%
#385
b1100 B
b111 A
0"
0G
1J
zH
1,
0)
b0 I
1%
#386
0%
#387
1J
zH
0"
0G
0,
1+
b1 I
1%
#388
0%
#389
1J
zH
1"
1G
0+
1*
b10 I
1%
#390
0%
#391
1J
zH
0*
1)
b11 I
bxzzzzzzzz #
bxzzzzzzzz (
bz E
1%
#392
0%
#393
1!
b1101 B
b0 A
b1100 C
0"
0G
0J
1H
1,
0)
b0 I
1%
#394
0%
#395
0"
0G
0,
1+
b1 I
1%
#396
0%
#397
1"
1G
0+
1*
b10 I
1%
#398
0%
#399
0*
1)
b11 I
1%
#400
0%
#401
b1110 B
b1101 C
0"
0G
1,
0)
b0 I
1%
#402
0%
#403
0!
0H
0"
0G
0,
1+
b1 I
1%
#404
0%
#405
0H
1"
1G
0+
1*
b10 I
1%
#406
0%
#407
1!
1H
0*
1)
b11 I
1%
#408
0%
#409
b1 B
b1110 C
1"
1G
1,
0)
b0 I
1%
#410
0%
#411
0,
1+
b1 I
1%
#412
0%
#413
0+
1*
b10 I
1%
#414
0%
#415
0*
1)
b11 I
1%
#416
0%
#417
b10 B
b1 C
1,
0)
b0 I
1%
#418
0%
#419
0!
0H
0,
1+
b1 I
1%
#420
0%
#421
0H
0+
1*
b10 I
1%
#422
0%
#423
0"
0G
0H
0*
1)
b11 I
1%
#424
0%
#425
b10 C
x!
xH
0"
0G
1,
0)
b0 I
1%
#426
0%
#427
0!
0H
0"
0G
0K
0,
1+
b1 I
1%
#428
0%
#429
0H
1"
1G
0+
1*
b10 I
1%
#430
0%
#431
0H
0*
1)
b11 I
1%
#432
0%
#433
b1 A
0"
0G
0H
1,
0)
b0 I
1%
#434
0%
#435
1!
1H
0"
0G
1K
0,
1+
b1 I
1%
#436
0%
#437
1"
1G
0+
1*
b10 I
1%
#438
0%
#439
0*
1)
b11 I
1%
#440
0%
#441
b10 A
0"
0G
1,
0)
b0 I
1%
#442
0%
#443
0"
0G
0,
1+
b1 I
1%
#444
0%
#445
1"
1G
0+
1*
b10 I
1%
#446
0%
#447
0*
1)
b11 I
1%
#448
0%
#449
b11 A
0"
0G
1,
0)
b0 I
1%
#450
0%
#451
0!
0H
0"
0G
0K
0,
1+
b1 I
1%
#452
0%
#453
0H
1"
1G
0+
1*
b10 I
1%
#454
0%
#455
0H
0*
1)
b11 I
1%
#456
0%
#457
b100 A
0"
0G
0H
1,
0)
b0 I
1%
#458
0%
#459
1!
1H
0"
0G
1K
0,
1+
b1 I
1%
#460
0%
#461
1"
1G
0+
1*
b10 I
1%
#462
0%
#463
0*
1)
b11 I
1%
#464
0%
#465
b101 A
0"
0G
1,
0)
b0 I
1%
#466
0%
#467
0"
0G
0,
1+
b1 I
1%
#468
0%
#469
1"
1G
0+
1*
b10 I
1%
#470
0%
#471
0*
1)
b11 I
1%
#472
0%
#473
b110 A
0"
0G
1,
0)
b0 I
1%
#474
0%
#475
0!
0H
0"
0G
0K
0,
1+
b1 I
1%
#476
0%
#477
0H
1"
1G
0+
1*
b10 I
1%
#478
0%
#479
0H
0*
1)
b11 I
1%
#480
0%
#481
b11 B
b111 A
0"
0G
0H
1,
0)
b0 I
1%
#482
0%
#483
0H
0"
0G
0,
1+
b1 I
1%
#484
0%
