fpga/spi/spi.v
// Copyright 2024
// Bryce's Senior Project
// Description: This is the RTL for SPI

module spi ( 
    input           reset_n,    // Active low reset
    input           clock,      // The main clock
    input           cs_n,       // Active low chip select
    input           mosi,       // Master out slave in

    output reg [15:0] shadow_reg  //The output of the SPI
);

wire shift_en;
reg [15:0] shift_reg;

// The shift_en is the clock masked by cs_n
assign shift_en = clock & (~cs_n);

// The shift_reg gets filled MSB to LSB with MOSI data
always @(posedge shift_en or negedge reset_n) begin
    if(~reset_n)
        shift_reg[15:0] <= 16'h0;
    else begin
        shift_reg [15:1] <= shift_reg[14:0];
        shift_reg[0] <= mosi;
    end
end

// The shadow_reg is updated from the shift_reg when cs_n is asserted
always @(posedge cs_n or negedge reset_n) begin
    if(~reset_n)
        shadow_reg[15:0] <= 16'h0;
    else 
        shadow_reg [15:0] <= shift_reg[15:0];
end
endmodule

fpga/spi/spi_tb.v
// Copyright 2024
// Bryce's Senior Project
// Description: This is the TestBench for SPI

module test();
  reg clock = 0;
  reg reset_n = 0;
  reg cs_n = 1;
  wire mosi;
  wire [15:0] shadow_reg;
  wire gated_clock;
  reg [15:0] mosi_reg;

 always
    #1  clock = ~clock;
assign gated_clock = clock & ~cs_n;

initial begin
    $display("Starting SPI test");
    
    $display("Deasserting reset");
    #10 reset_n = 1;

    $display("Asserting cs_n");
    #2 cs_n = 0;

    $display("Running for 16 cycles");
    #32;

    $display("Deasserting cs_n");
    cs_n = 1;

    #10 $finish;
end

always @(negedge gated_clock or negedge reset_n) begin
    if(~reset_n)
        mosi_reg[15:0] <= 16'hDEAD;
    else
        mosi_reg[15:1] <= mosi_reg[14:0];
end

assign mosi = mosi_reg[15];

    spi dut(
        .reset_n        (reset_n),
        .clock          (clock),
        .cs_n           (cs_n),
        .mosi           (mosi),
        .shadow_reg     (shadow_reg)
    );

initial begin
    $dumpfile("spi.vcd");
    $dumpvars(0,test);
  end

endmodule

fpga/spi/spi.vcd
$date
	Sun Jul 28 15:52:00 2024
$end
$version
	Icarus Verilog
$end
$timescale
	1s
$end
$scope module test $end
$var wire 1 ! gated_clock $end
$var wire 16 " shadow_reg [15:0] $end
$var wire 1 # mosi $end
$var reg 1 $ clock $end
$var reg 1 % cs_n $end
$var reg 16 & mosi_reg [15:0] $end
$var reg 1 ' reset_n $end
$scope module dut $end
$var wire 1 $ clock $end
$var wire 1 % cs_n $end
$var wire 1 # mosi $end
$var wire 1 ' reset_n $end
$var wire 1 ( shift_en $end
$var reg 16 ) shadow_reg [15:0] $end
$var reg 16 * shift_reg [15:0] $end
$upscope $end
$upscope $end
$enddefinitions $end
$comment Show the parameter values. $end
$dumpall
$end
#0
$dumpvars
b0 *
b0 )
0(
0'
b1101111010101101 &
1%
0$
1#
b0 "
0!
$end
#1
1$
#2
0$
#3
1$
#4
0$
#5
1$
#6
0$
#7
1$
#8
0$
#9
1$
#10
0$
1'
#11
1$
#12
0$
0%
#13
b1 *
1(
1!
1$
#14
b1011110101011011 &
0(
0!
0$
#15
b11 *
1(
1!
1$
#16
0#
b111101010110111 &
0(
0!
0$
#17
b110 *
1(
1!
1$
#18
1#
b1111010101101111 &
0(
0!
0$
#19
b1101 *
1(
1!
1$
#20
b1110101011011111 &
0(
0!
0$
#21
b11011 *
1(
1!
1$
#22
b1101010110111111 &
0(
0!
0$
#23
b110111 *
1(
1!
1$
#24
b1010101101111111 &
0(
0!
0$
#25
b1101111 *
1(
1!
1$
#26
0#
b101011011111111 &
0(
0!
0$
#27
b11011110 *
1(
1!
1$
#28
1#
b1010110111111111 &
0(
0!
0$
#29
b110111101 *
1(
1!
1$
#30
0#
b101101111111111 &
0(
0!
0$
#31
b1101111010 *
1(
1!
1$
#32
1#
b1011011111111111 &
0(
0!
0$
#33
b11011110101 *
1(
1!
1$
#34
0#
b110111111111111 &
0(
0!
0$
#35
b110111101010 *
1(
1!
1$
#36
1#
b1101111111111111 &
0(
0!
0$
#37
b1101111010101 *
1(
1!
1$
#38
b1011111111111111 &
0(
0!
0$
#39
b11011110101011 *
1(
1!
1$
#40
0#
b111111111111111 &
0(
0!
0$
#41
b110111101010110 *
1(
1!
1$
#42
1#
b1111111111111111 &
0(
0!
0$
#43
b1101111010101101 *
1(
1!
1$
#44
b1101111010101101 "
b1101111010101101 )
0(
0!
0$
1%
